stimulsoft_data_adapters/StiCsvAdapter.py
stimulsoft_data_adapters/StiDataAdapter.py
stimulsoft_data_adapters/StiFileAdapter.py
stimulsoft_data_adapters/StiFirebirdAdapter.py
stimulsoft_data_adapters/StiJsonAdapter.py
stimulsoft_data_adapters/StiMongoDbAdapter.py
stimulsoft_data_adapters/StiMsSqlAdapter.py
stimulsoft_data_adapters/StiMySqlAdapter.py
stimulsoft_data_adapters/StiOdbcAdapter.py
stimulsoft_data_adapters/StiOracleAdapter.py
stimulsoft_data_adapters/StiPostgreSqlAdapter.py
stimulsoft_data_adapters/StiSqlAdapter.py
stimulsoft_data_adapters/StiXmlAdapter.py
stimulsoft_data_adapters/__init__.py
stimulsoft_data_adapters/classes/StiBaseHandler.py
stimulsoft_data_adapters/classes/StiBaseRequest.py
stimulsoft_data_adapters/classes/StiBaseResponse.py
stimulsoft_data_adapters/classes/StiBaseResult.py
stimulsoft_data_adapters/classes/StiConnectionInfo.py
stimulsoft_data_adapters/classes/StiDataResult.py
stimulsoft_data_adapters/classes/StiFunctions.py
stimulsoft_data_adapters/classes/StiParameter.py
stimulsoft_data_adapters/classes/StiPath.py
stimulsoft_data_adapters/classes/__init__.py
stimulsoft_data_adapters/enums/StiBaseEventType.py
stimulsoft_data_adapters/enums/StiDataCommand.py
stimulsoft_data_adapters/enums/StiDataType.py
stimulsoft_data_adapters/enums/StiDatabaseType.py
stimulsoft_data_adapters/enums/StiFrameworkType.py
stimulsoft_data_adapters/enums/__init__.py
stimulsoft_data_adapters/events/StiConnectionEventArgs.py
stimulsoft_data_adapters/events/StiDataEventArgs.py
stimulsoft_data_adapters/events/StiEvent.py
stimulsoft_data_adapters/events/StiEventArgs.py
stimulsoft_data_adapters/events/__init__.py
stimulsoft_data_adapters-2026.1.2.dist-info/licenses/LICENSE.md
stimulsoft_data_adapters-2026.1.2.dist-info/METADATA
stimulsoft_data_adapters-2026.1.2.dist-info/WHEEL
stimulsoft_data_adapters-2026.1.2.dist-info/top_level.txt
stimulsoft_data_adapters-2026.1.2.dist-info/RECORD
