Metadata-Version: 2.4
Name: stimulsoft_data_adapters
Version: 2026.1.2
Summary: Stimulsoft data adapters for Python.
Home-page: https://www.stimulsoft.com/en/products/reports-python
Author: Stimulsoft
Author-email: info@stimulsoft.com
License: https://www.stimulsoft.com/en/licensing/developers
Classifier: License :: Other/Proprietary License
Classifier: Framework :: Django
Classifier: Framework :: Flask
Classifier: Programming Language :: Python
Classifier: Programming Language :: Python :: 3.10
Classifier: Programming Language :: Python :: 3.11
Classifier: Programming Language :: Python :: 3.12
Classifier: Topic :: Database
Classifier: Topic :: Software Development
Requires-Python: >=3.10
License-File: LICENSE.md
Requires-Dist: pyodbc
Requires-Dist: requests
Provides-Extra: ext
Requires-Dist: pyodbc; extra == "ext"
Requires-Dist: pymssql; extra == "ext"
Requires-Dist: mysql-connector-python; extra == "ext"
Requires-Dist: psycopg; extra == "ext"
Requires-Dist: firebird-driver; extra == "ext"
Requires-Dist: oracledb; extra == "ext"
Requires-Dist: pymongo[srv]; extra == "ext"
Dynamic: author
Dynamic: author-email
Dynamic: classifier
Dynamic: description
Dynamic: description-content-type
Dynamic: home-page
Dynamic: license
Dynamic: license-file
Dynamic: provides-extra
Dynamic: requires-dist
Dynamic: requires-python
Dynamic: summary
